Workbook

Sheet Dashboard
A1: Asset Dashboard
A2: Live formulas over the Endpoints and Servers sheets - add rows there and everything here updates. Windows includes Windows Server.
A4: Total assets | B4: Active | C4: With EDR | D4: EDR coverage | E4: Without EDR
A5: =B14 | B5: =C14 | C5: =D14 | D5: =IF(B14=0,0,D14/B14) | E5: =E14
A9: Assets by OS (endpoints + servers)
A10: OS | B10: Total | C10: Active | D10: EDR Installed | E10: No EDR
A11: Windows | B11: =COUNTIF(Endpoints!$D:$D,"Windows")+COUNTIF(Servers!$D:$D,"Windows Server") | C11: =COUNTIFS(Endpoints!$D:$D,"Windows",Endpoints!$M:$M,"Active")+COUNTIFS(Servers!$D:$D,"Windows Server",Servers!$S:$S,"Active") | D11: =COUNTIFS(Endpoints!$D:$D,"Windows",Endpoints!$P:$P,"<>Not Installed",Endpoints!$P:$P,"<>")+COUNTIFS(Servers!$D:$D,"Windows Server",Servers!$Q:$Q,"<>Not Installed",Servers!$Q:$Q,"<>") | E11: =B11-D11
A12: macOS | B12: =COUNTIF(Endpoints!$D:$D,"macOS")+COUNTIF(Servers!$D:$D,"macOS") | C12: =COUNTIFS(Endpoints!$D:$D,"macOS",Endpoints!$M:$M,"Active")+COUNTIFS(Servers!$D:$D,"macOS",Servers!$S:$S,"Active") | D12: =COUNTIFS(Endpoints!$D:$D,"macOS",Endpoints!$P:$P,"<>Not Installed",Endpoints!$P:$P,"<>")+COUNTIFS(Servers!$D:$D,"macOS",Servers!$Q:$Q,"<>Not Installed",Servers!$Q:$Q,"<>") | E12: =B12-D12
A13: Linux | B13: =COUNTIF(Endpoints!$D:$D,"Linux")+COUNTIF(Servers!$D:$D,"Linux") | C13: =COUNTIFS(Endpoints!$D:$D,"Linux",Endpoints!$M:$M,"Active")+COUNTIFS(Servers!$D:$D,"Linux",Servers!$S:$S,"Active") | D13: =COUNTIFS(Endpoints!$D:$D,"Linux",Endpoints!$P:$P,"<>Not Installed",Endpoints!$P:$P,"<>")+COUNTIFS(Servers!$D:$D,"Linux",Servers!$Q:$Q,"<>Not Installed",Servers!$Q:$Q,"<>") | E13: =B13-D13
A14: Total | B14: =SUM(B11:B13) | C14: =SUM(C11:C13) | D14: =SUM(D11:D13) | E14: =SUM(E11:E13)
A17: Endpoints last seen, by month (last 12 months)
A18: Month | B18: Endpoints | C18: Month start
A19: =TEXT(C19,"mmm yyyy") | B19: =COUNTIFS(Endpoints!$S:$S,">="&C19,Endpoints!$S:$S,"<"&EDATE(C19,1)) | C19: =EDATE(DATE(YEAR(TODAY()),MONTH(TODAY()),1),-11)
A20: =TEXT(C20,"mmm yyyy") | B20: =COUNTIFS(Endpoints!$S:$S,">="&C20,Endpoints!$S:$S,"<"&EDATE(C20,1)) | C20: =EDATE(DATE(YEAR(TODAY()),MONTH(TODAY()),1),-10)
A21: =TEXT(C21,"mmm yyyy") | B21: =COUNTIFS(Endpoints!$S:$S,">="&C21,Endpoints!$S:$S,"<"&EDATE(C21,1)) | C21: =EDATE(DATE(YEAR(TODAY()),MONTH(TODAY()),1),-9)
A22: =TEXT(C22,"mmm yyyy") | B22: =COUNTIFS(Endpoints!$S:$S,">="&C22,Endpoints!$S:$S,"<"&EDATE(C22,1)) | C22: =EDATE(DATE(YEAR(TODAY()),MONTH(TODAY()),1),-8)
A23: =TEXT(C23,"mmm yyyy") | B23: =COUNTIFS(Endpoints!$S:$S,">="&C23,Endpoints!$S:$S,"<"&EDATE(C23,1)) | C23: =EDATE(DATE(YEAR(TODAY()),MONTH(TODAY()),1),-7)
A24: =TEXT(C24,"mmm yyyy") | B24: =COUNTIFS(Endpoints!$S:$S,">="&C24,Endpoints!$S:$S,"<"&EDATE(C24,1)) | C24: =EDATE(DATE(YEAR(TODAY()),MONTH(TODAY()),1),-6)
A25: =TEXT(C25,"mmm yyyy") | B25: =COUNTIFS(Endpoints!$S:$S,">="&C25,Endpoints!$S:$S,"<"&EDATE(C25,1)) | C25: =EDATE(DATE(YEAR(TODAY()),MONTH(TODAY()),1),-5)
A26: =TEXT(C26,"mmm yyyy") | B26: =COUNTIFS(Endpoints!$S:$S,">="&C26,Endpoints!$S:$S,"<"&EDATE(C26,1)) | C26: =EDATE(DATE(YEAR(TODAY()),MONTH(TODAY()),1),-4)
A27: =TEXT(C27,"mmm yyyy") | B27: =COUNTIFS(Endpoints!$S:$S,">="&C27,Endpoints!$S:$S,"<"&EDATE(C27,1)) | C27: =EDATE(DATE(YEAR(TODAY()),MONTH(TODAY()),1),-3)
A28: =TEXT(C28,"mmm yyyy") | B28: =COUNTIFS(Endpoints!$S:$S,">="&C28,Endpoints!$S:$S,"<"&EDATE(C28,1)) | C28: =EDATE(DATE(YEAR(TODAY()),MONTH(TODAY()),1),-2)
A29: =TEXT(C29,"mmm yyyy") | B29: =COUNTIFS(Endpoints!$S:$S,">="&C29,Endpoints!$S:$S,"<"&EDATE(C29,1)) | C29: =EDATE(DATE(YEAR(TODAY()),MONTH(TODAY()),1),-1)
A30: =TEXT(C30,"mmm yyyy") | B30: =COUNTIFS(Endpoints!$S:$S,">="&C30,Endpoints!$S:$S,"<"&EDATE(C30,1)) | C30: =EDATE(DATE(YEAR(TODAY()),MONTH(TODAY()),1),0)
A31: Older than 12 months / never seen | B31: =COUNTA(Endpoints!$A:$A)-1-SUM(B19:B30)

Sheet Summary
A1: Company Asset Inventory - Summary (SAMPLE DATA)
A2: All figures below are live formulas over the Endpoints, Servers and Registers sheets. Data is fictional.
A4: Endpoints by OS
A5: OS Family | B5: Total | C5: Active | D5: No EDR | E5: Not Encrypted
A6: Windows | B6: =COUNTIF(Endpoints!$D:$D,A6) | C6: =COUNTIFS(Endpoints!$D:$D,A6,Endpoints!$M:$M,"Active") | D6: =COUNTIFS(Endpoints!$D:$D,A6,Endpoints!$P:$P,"Not Installed") | E6: =COUNTIFS(Endpoints!$D:$D,A6,Endpoints!$R:$R,"No")
A7: macOS | B7: =COUNTIF(Endpoints!$D:$D,A7) | C7: =COUNTIFS(Endpoints!$D:$D,A7,Endpoints!$M:$M,"Active") | D7: =COUNTIFS(Endpoints!$D:$D,A7,Endpoints!$P:$P,"Not Installed") | E7: =COUNTIFS(Endpoints!$D:$D,A7,Endpoints!$R:$R,"No")
A8: Linux | B8: =COUNTIF(Endpoints!$D:$D,A8) | C8: =COUNTIFS(Endpoints!$D:$D,A8,Endpoints!$M:$M,"Active") | D8: =COUNTIFS(Endpoints!$D:$D,A8,Endpoints!$P:$P,"Not Installed") | E8: =COUNTIFS(Endpoints!$D:$D,A8,Endpoints!$R:$R,"No")
A9: Total | B9: =SUM(B6:B8) | C9: =SUM(C6:C8) | D9: =SUM(D6:D8) | E9: =SUM(E6:E8)
A11: Servers by OS
A12: OS Family | B12: Total | C12: Production | D12: Tier 0/1 | E12: No EDR | F12: Not Patched
A13: Windows Server | B13: =COUNTIF(Servers!$D:$D,A13) | C13: =COUNTIFS(Servers!$D:$D,A13,Servers!$G:$G,"Production") | D13: =COUNTIFS(Servers!$D:$D,A13,Servers!$N:$N,"Tier 0")+COUNTIFS(Servers!$D:$D,A13,Servers!$N:$N,"Tier 1") | E13: =COUNTIFS(Servers!$D:$D,A13,Servers!$Q:$Q,"Not Installed") | F13: =COUNTIFS(Servers!$D:$D,A13,Servers!$O:$O,"Not Patched")
A14: Linux | B14: =COUNTIF(Servers!$D:$D,A14) | C14: =COUNTIFS(Servers!$D:$D,A14,Servers!$G:$G,"Production") | D14: =COUNTIFS(Servers!$D:$D,A14,Servers!$N:$N,"Tier 0")+COUNTIFS(Servers!$D:$D,A14,Servers!$N:$N,"Tier 1") | E14: =COUNTIFS(Servers!$D:$D,A14,Servers!$Q:$Q,"Not Installed") | F14: =COUNTIFS(Servers!$D:$D,A14,Servers!$O:$O,"Not Patched")
A15: macOS | B15: =COUNTIF(Servers!$D:$D,A15) | C15: =COUNTIFS(Servers!$D:$D,A15,Servers!$G:$G,"Production") | D15: =COUNTIFS(Servers!$D:$D,A15,Servers!$N:$N,"Tier 0")+COUNTIFS(Servers!$D:$D,A15,Servers!$N:$N,"Tier 1") | E15: =COUNTIFS(Servers!$D:$D,A15,Servers!$Q:$Q,"Not Installed") | F15: =COUNTIFS(Servers!$D:$D,A15,Servers!$O:$O,"Not Patched")
A16: Total | B16: =SUM(B13:B15) | C16: =SUM(C13:C15) | D16: =SUM(D13:D15) | E16: =SUM(E13:E15) | F16: =SUM(F13:F15)
A18: Registers
A19: Category | B19: Items | C19: Annual Cost (INR)
A20: Software License | B20: =COUNTIF(Registers!$B:$B,A20) | C20: =SUMIF(Registers!$B:$B,A20,Registers!$G:$G)
A21: Network Device | B21: =COUNTIF(Registers!$B:$B,A21) | C21: =SUMIF(Registers!$B:$B,A21,Registers!$G:$G)
A22: Cloud Account | B22: =COUNTIF(Registers!$B:$B,A22) | C22: =SUMIF(Registers!$B:$B,A22,Registers!$G:$G)
A23: Mobile Device | B23: =COUNTIF(Registers!$B:$B,A23) | C23: =SUMIF(Registers!$B:$B,A23,Registers!$G:$G)
A24: Domain / Certificate | B24: =COUNTIF(Registers!$B:$B,A24) | C24: =SUMIF(Registers!$B:$B,A24,Registers!$G:$G)
A25: Total | B25: =SUM(B20:B24) | C25: =SUM(C20:C24)
A27: Grand total assets (endpoints + servers) | B27: =B9+B16
A28: Endpoints not seen in 30+ days | B28: =COUNTIF(Endpoints!$S:$S,"<"&(DATE(2026,10,13)-30))
A29: Report date (assumption: fixed sample date) | B29: 46308

Sheet Endpoints
A1: Asset ID | B1: Hostname | C1: Type | D1: OS Family | E1: OS Version | F1: Model | G1: Serial Number | H1: IP Address | I1: MAC Address | J1: Owner | K1: Department | L1: Location | M1: Status | N1: Purchase Date | O1: Warranty End | P1: EDR Agent | Q1: MDM / Mgmt | R1: Disk Encrypted | S1: Last Seen
A2: AST-0001 | B2: WIN-1409 | C2: Laptop | D2: Windows | E2: Windows 10 22H2 | F2: HP EliteBook 840 G10 | G2: SN42868828 | H2: 10.24.35.190 | I2: A5:F4:21:85:AB:64 | J2: Aarav Mehta | K2: Engineering | L2: Bengaluru HQ | M2: Active | N2: 44939 | O2: 46034 | P2: CrowdStrike Falcon | Q2: Intune | R2: Yes | S2: 46308
A3: AST-0002 | B3: WIN-4257 | C3: Laptop | D3: Windows | E3: Windows 10 22H2 | F3: Lenovo ThinkPad T14 | G3: SN83140807 | H3: 10.36.56.116 | I3: E2:01:99:64:AB:53 | J3: Vikram Rao | K3: HR | L3: Mumbai | M3: Active | N3: 45016 | O3: 46111 | P3: CrowdStrike Falcon | Q3: Intune | R3: Yes | S3: 46308
A4: AST-0003 | B4: WIN-6881 | C4: Laptop | D4: Windows | E4: Windows 11 24H2 | F4: Lenovo ThinkPad T14 | G4: SN45503389 | H4: 10.12.186.119 | I4: 4A:3A:80:47:AB:90 | J4: Divya Menon | K4: Security | L4: Pune | M4: Active | N4: 45470 | O4: 46565 | P4: CrowdStrike Falcon | Q4: Intune | R4: Yes | S4: 46308
A5: AST-0004 | B5: WIN-5741 | C5: Laptop | D5: Windows | E5: Windows 11 23H2 | F5: Dell Latitude 5440 | G5: SN23556182 | H5: 10.34.71.118 | I5: 5C:1C:55:36:AB:95 | J5: Vikram Rao | K5: Finance | L5: Pune | M5: Active | N5: 44894 | O5: 45989 | P5: CrowdStrike Falcon | Q5: Intune | R5: Yes | S5: 46307
A6: AST-0005 | B6: WIN-7216 | C6: Laptop | D6: Windows | E6: Windows 11 24H2 | F6: Lenovo ThinkPad T14 | G6: SN84752529 | H6: 10.24.175.85 | I6: 0B:0C:61:44:AB:18 | J6: Sneha Iyer | K6: Security | L6: Mumbai | M6: Active | N6: 45914 | O6: 47009 | P6: CrowdStrike Falcon | Q6: Intune | R6: Yes | S6: 46303
A7: AST-0006 | B7: WIN-3287 | C7: Laptop | D7: Windows | E7: Windows 11 23H2 | F7: Lenovo ThinkPad T14 | G7: SN85345555 | H7: 10.44.67.193 | I7: E3:E3:56:38:AB:27 | J7: Imran Khan | K7: Legal | L7: Bengaluru HQ | M7: Active | N7: 45956 | O7: 47051 | P7: CrowdStrike Falcon | Q7: Intune | R7: Yes | S7: 46307
A8: AST-0007 | B8: WIN-7916 | C8: Laptop | D8: Windows | E8: Windows 10 22H2 | F8: Dell Latitude 5440 | G8: SN61642594 | H8: 10.34.152.121 | I8: 42:40:97:24:AB:97 | J8: Imran Khan | K8: IT Ops | L8: Remote | M8: Active | N8: 44963 | O8: 46058 | P8: CrowdStrike Falcon | Q8: Intune | R8: Yes | S8: 46308
A9: AST-0008 | B9: WIN-8433 | C9: Laptop | D9: Windows | E9: Windows 11 23H2 | F9: Lenovo ThinkPad T14 | G9: SN45351479 | H9: 10.42.195.47 | I9: 4A:52:91:74:AB:87 | J9: Sneha Iyer | K9: HR | L9: Delhi NCR | M9: Active | N9: 45358 | O9: 46453 | P9: CrowdStrike Falcon | Q9: Intune | R9: Yes | S9: 46308
A10: AST-0009 | B10: WIN-6310 | C10: Laptop | D10: Windows | E10: Windows 11 24H2 | F10: Dell Latitude 5440 | G10: SN25014631 | H10: 10.33.224.254 | I10: 2B:0B:82:20:AB:20 | J10: Meera Pillai | K10: Finance | L10: Pune | M10: Active | N10: 46247 | O10: 47342 | P10: CrowdStrike Falcon | Q10: Intune | R10: Yes | S10: 46293
A11: AST-0010 | B11: WIN-5342 | C11: Laptop | D11: Windows | E11: Windows 10 22H2 | F11: Lenovo ThinkPad T14 | G11: SN66792612 | H11: 10.23.237.140 | I11: FF:BF:49:61:AB:95 | J11: Anita Das | K11: Legal | L11: Pune | M11: Active | N11: 45123 | O11: 46218 | P11: CrowdStrike Falcon | Q11: Intune | R11: Yes | S11: 46308
A12: AST-0011 | B12: WIN-6539 | C12: Laptop | D12: Windows | E12: Windows 11 23H2 | F12: Lenovo ThinkPad T14 | G12: SN84346088 | H12: 10.24.150.58 | I12: 0A:F5:17:39:AB:18 | J12: Aarav Mehta | K12: Security | L12: Bengaluru HQ | M12: In Repair | N12: 45788 | O12: 46883 | P12: CrowdStrike Falcon | Q12: Intune | R12: Yes | S12: 46308
A13: AST-0012 | B13: WIN-4510 | C13: Laptop | D13: Windows | E13: Windows 10 22H2 | F13: Dell Latitude 5440 | G13: SN86644106 | H13: 10.46.121.64 | I13: D3:BA:22:94:AB:65 | J13: Anita Das | K13: Marketing | L13: Hyderabad | M13: Active | N13: 44878 | O13: 45973 | P13: CrowdStrike Falcon | Q13: Intune | R13: Yes | S13: 46303
... A47: AST-0046 | B47: LNX-5728 | C47: Laptop | D47: Linux | E47: Ubuntu 24.04 LTS | F47: Dell XPS 15 | G47: SN72907576 | H47: 10.54.77.181 | I47: 32:44:73:66:AB:20 | J47: Divya Menon | K47: Engineering | L47: Hyderabad | M47: Active | N47: 45909 | O47: 47004 | P47: Not Installed | Q47: Ansible | R47: Yes | S47: 46307

Sheet Servers
A1: Asset ID | B1: Hostname | C1: Role | D1: OS Family | E1: OS Version | F1: Platform | G1: Environment | H1: vCPU | I1: RAM (GB) | J1: IP Address | K1: Data Center / Region | L1: Owning Team | M1: Owner | N1: Criticality | O1: Patch Cadence | P1: Last Patched | Q1: EDR Agent | R1: Backup | S1: Status
A2: SRV-0001 | B2: WSRV-PRO-12 | C2: File Server | D2: Windows Server | E2: Windows Server 2016 | F2: Physical - HPE DL380 | G2: Production | H2: 64 | I2: 16 | J2: 10.124.172.212 | K2: AWS ap-south-1 | L2: IT Ops | M2: Rohan Gupta | N2: Tier 2 | O2: Not Patched | P2: 46224 | Q2: CrowdStrike Falcon | R2: Commvault | S2: Active
A3: SRV-0002 | B3: WSRV-DEV-82 | C3: IIS Web Server | D3: Windows Server | E3: Windows Server 2019 | F3: Physical - Dell R750 | G3: Dev | H3: 16 | I3: 128 | J3: 10.110.82.173 | K3: Bengaluru DC | L3: Engineering | M3: Anita Das | N3: Tier 2 | O3: Quarterly | P3: 46271 | Q3: CrowdStrike Falcon | R3: Veeam | S3: Active
A4: SRV-0003 | B4: WSRV-PRO-41 | C4: SQL Server | D4: Windows Server | E4: Windows Server 2022 | F4: VMware VM | G4: Production | H4: 32 | I4: 256 | J4: 10.126.252.2 | K4: Azure Central India | L4: Finance | M4: Aarav Mehta | N4: Tier 1 | O4: Not Patched | P4: 46261 | Q4: Not Installed | R4: None | S4: Active
A5: SRV-0004 | B5: WSRV-PRO-27 | C5: SQL Server | D5: Windows Server | E5: Windows Server 2016 | F5: AWS EC2 | G5: Production | H5: 16 | I5: 128 | J5: 10.128.178.126 | K5: Bengaluru DC | L5: IT Ops | M5: Divya Menon | N5: Tier 1 | O5: Monthly | P5: 46268 | Q5: CrowdStrike Falcon | R5: Veeam | S5: Active
A6: SRV-0005 | B6: WSRV-DEV-12 | C6: File Server | D6: Windows Server | E6: Windows Server 2019 | F6: Physical - Dell R750 | G6: Dev | H6: 4 | I6: 32 | J6: 10.115.238.185 | K6: AWS ap-south-1 | L6: Security | M6: Karan Shah | N6: Tier 2 | O6: Quarterly | P6: 46276 | Q6: CrowdStrike Falcon | R6: Veeam | S6: Active
A7: SRV-0006 | B7: WSRV-PRO-77 | C7: Print Server | D7: Windows Server | E7: Windows Server 2016 | F7: AWS EC2 | G7: Production | H7: 4 | I7: 64 | J7: 10.124.202.220 | K7: Azure Central India | L7: Security | M7: Imran Khan | N7: Tier 1 | O7: Monthly | P7: 46271 | Q7: CrowdStrike Falcon | R7: None | S7: Active
A8: SRV-0007 | B8: WSRV-DEV-69 | C8: IIS Web Server | D8: Windows Server | E8: Windows Server 2022 | F8: Azure VM | G8: Dev | H8: 64 | I8: 256 | J8: 10.112.116.240 | K8: AWS ap-south-1 | L8: Engineering | M8: Sneha Iyer | N8: Tier 3 | O8: Quarterly | P8: 46278 | Q8: CrowdStrike Falcon | R8: Veeam | S8: Active
A9: SRV-0008 | B9: WSRV-DEV-91 | C9: IIS Web Server | D9: Windows Server | E9: Windows Server 2022 | F9: AWS EC2 | G9: Dev | H9: 32 | I9: 16 | J9: 10.104.128.249 | K9: AWS ap-south-1 | L9: IT Ops | M9: Meera Pillai | N9: Tier 0 | O9: Not Patched | P9: 46191 | Q9: CrowdStrike Falcon | R9: Veeam | S9: Active
A10: SRV-0009 | B10: WSRV-DEV-84 | C10: File Server | D10: Windows Server | E10: Windows Server 2019 | F10: Physical - Dell R750 | G10: Dev | H10: 16 | I10: 64 | J10: 10.119.177.103 | K10: Bengaluru DC | L10: Security | M10: Imran Khan | N10: Tier 2 | O10: Weekly | P10: 46227 | Q10: CrowdStrike Falcon | R10: Veeam | S10: Decommissioning
A11: SRV-0010 | B11: WSRV-PRO-31 | C11: SQL Server | D11: Windows Server | E11: Windows Server 2019 | F11: VMware VM | G11: Production | H11: 32 | I11: 16 | J11: 10.124.162.182 | K11: Bengaluru DC | L11: Finance | M11: Rohan Gupta | N11: Tier 1 | O11: Monthly | P11: 46302 | Q11: CrowdStrike Falcon | R11: Veeam | S11: Active
A12: SRV-0011 | B12: LSRV-UAT-48 | C12: Kubernetes Node | D12: Linux | E12: RHEL 9 | F12: AWS EC2 | G12: UAT | H12: 64 | I12: 128 | J12: 10.118.174.204 | K12: Mumbai DC | L12: Engineering | M12: Rohan Gupta | N12: Tier 0 | O12: Not Patched | P12: 46196 | Q12: CrowdStrike Falcon | R12: Veeam | S12: Active
A13: SRV-0012 | B13: LSRV-PRO-30 | C13: Kubernetes Node | D13: Linux | E13: Ubuntu 22.04 LTS | F13: Physical - Dell R750 | G13: Production | H13: 16 | I13: 16 | J13: 10.128.205.121 | K13: AWS ap-south-1 | L13: Engineering | M13: Priya Nair | N13: Tier 2 | O13: Weekly | P13: 46232 | Q13: CrowdStrike Falcon | R13: None | S13: Active
... A27: SRV-0026 | B27: MSRV-DEV-76 | C27: CI Build Runner | D27: macOS | E27: macOS 14 Server Host | F27: Physical - Dell R750 | G27: Dev | H27: 32 | I27: 64 | J27: 10.127.170.242 | K27: Azure Central India | L27: IT Ops | M27: Vikram Rao | N27: Tier 3 | O27: Weekly | P27: 46262 | Q27: CrowdStrike Falcon | R27: Veeam | S27: Active

Sheet Registers
A1: Register ID | B1: Category | C1: Item | D1: Vendor | E1: Owner | F1: Quantity | G1: Annual Cost (INR) | H1: Renewal / Expiry | I1: Notes
A2: REG-0001 | B2: Software License | C2: Microsoft 365 E5 | D2: Microsoft | E2: Meera Pillai | F2: 60 | G2: 228000 | H2: 46442 | I2: Per-user annual (qty x unit price)
A3: REG-0002 | B3: Software License | C3: CrowdStrike Falcon Prevent | D3: CrowdStrike | E3: Priya Nair | F3: 70 | G3: 168000 | H3: 46507 | I3: Per-user annual (qty x unit price)
A4: REG-0003 | B4: Software License | C4: JAMF Pro | D4: JAMF | E4: Imran Khan | F4: 20 | G4: 30000 | H4: 46516 | I4: Per-user annual (qty x unit price)
A5: REG-0004 | B5: Software License | C5: Slack Enterprise | D5: Salesforce | E5: Priya Nair | F5: 60 | G5: 114000 | H5: 46470 | I5: Per-user annual (qty x unit price)
A6: REG-0005 | B6: Software License | C6: Atlassian Jira Cloud | D6: Atlassian | E6: Divya Menon | F6: 40 | G6: 44000 | H6: 46443 | I6: Per-user annual (qty x unit price)
A7: REG-0006 | B7: Software License | C7: GitHub Enterprise | D7: GitHub | E7: Karan Shah | F7: 35 | G7: 73500 | H7: 46615 | I7: Per-user annual (qty x unit price)
A8: REG-0007 | B8: Software License | C8: Zoom Business | D8: Zoom | E8: Divya Menon | F8: 60 | G8: 84000 | H8: 46642 | I8: Per-user annual (qty x unit price)
A9: REG-0008 | B9: Software License | C9: Okta Workforce Identity | D9: Okta | E9: Imran Khan | F9: 60 | G9: 108000 | H9: 46341 | I9: Per-user annual (qty x unit price)
A10: REG-0009 | B10: Network Device | C10: Palo Alto PA-3410 Firewall | D10: Palo Alto Networks | E10: Vikram Rao | F10: 2 | G10: 45000 | H10: 46397 | I10: Support contract end date shown
A11: REG-0010 | B11: Network Device | C11: Cisco Catalyst 9300 Switch | D11: Cisco | E11: Vikram Rao | F11: 6 | G11: 95000 | H11: 46647 | I11: Support contract end date shown
A12: REG-0011 | B12: Network Device | C12: Aruba AP-535 Access Point | D12: HPE Aruba | E12: Vikram Rao | F12: 18 | G12: 45000 | H12: 46715 | I12: Support contract end date shown
A13: REG-0012 | B13: Network Device | C13: F5 BIG-IP LTM | D13: F5 | E13: Vikram Rao | F13: 2 | G13: 45000 | H13: 46374 | I13: Support contract end date shown
A14: REG-0013 | B14: Cloud Account | C14: AWS Account - Prod | D14: AWS | E14: Rohan Gupta | F14: 1 | G14: 120000 | H14: Pay-as-you-go | I14: Monthly billing
A15: REG-0014 | B15: Cloud Account | C15: AWS Account - Dev | D15: AWS | E15: Divya Menon | F15: 1 | G15: 90000 | H15: Pay-as-you-go | I15: Monthly billing
A16: REG-0015 | B16: Cloud Account | C16: Azure Subscription - Corp | D16: Microsoft | E16: Priya Nair | F16: 1 | G16: 120000 | H16: Pay-as-you-go | I16: Monthly billing
A17: REG-0016 | B17: Cloud Account | C17: Cloudflare Enterprise | D17: Cloudflare | E17: Aarav Mehta | F17: 1 | G17: 450000 | H17: Pay-as-you-go | I17: Monthly billing
A18: REG-0017 | B18: Mobile Device | C18: iPhone 15 (corporate) | D18: Apple | E18: IT Ops | F18: 12 | G18: 70000 | H18: N/A | I18: Managed via Intune
A19: REG-0018 | B19: Mobile Device | C19: Samsung Galaxy S24 (corporate) | D19: Samsung | E19: IT Ops | F19: 6 | G19: 65000 | H19: N/A | I19: Managed via Intune
A20: REG-0019 | B20: Domain / Certificate | C20: *.example-corp.com wildcard cert | D20: DigiCert | E20: Security | F20: 1 | G20: 35000 | H20: 46383 | I20: Auto-renew off
A21: REG-0020 | B21: Domain / Certificate | C21: example-corp.com domain | D21: GoDaddy | E21: IT Ops | F21: 1 | G21: 2500 | H21: 46518
